mixsqpx/__init__.py
mixsqpx/_version.py
mixsqpx/cpu_ops.cpython-312-x86_64-linux-gnu.so
mixsqpx/libarmadillo.so.14
mixsqpx/libarmadillo.so.14.4.3
mixsqpx/libarpack.so.2
mixsqpx/libarpack.so.2.1.0
mixsqpx/libblas.so.3
mixsqpx/liblapack.so.3
mixsqpx/libopenblas.so.0
mixsqpx/libopenblasp-r0.3.29.so
mixsqpx/mixsqp_jax.py
mixsqpx.libs/libgfortran-d53e3612.so.5.0.0
mixsqpx.libs/libquadmath-417181fc.so.0.0.0
mixsqpx-0.1.4.dist-info/METADATA
mixsqpx-0.1.4.dist-info/WHEEL
mixsqpx-0.1.4.dist-info/RECORD
mixsqpx-0.1.4.dist-info/licenses/LICENSE
