Metadata-Version: 2.1
Name: mixsqpx
Version: 0.1.4
Summary: jax inteface to a C++ implementation of the mixsqp algorithm
Author-Email: Paul Diegert <pdiegert@gmail.com>
License: MIT License
Requires-Python: <3.13,>=3.12
Requires-Dist: jax<=0.6.0,>=0.5.0
Requires-Dist: jaxlib<=0.6.0,>=0.5.0
